{
  "success": true,
  "result": "{\"stake\":\"nl5\",\"blinds\":\"$0.02/$0.05\",\"date\":\"2025-12-25\",\"dateText\":\"ui-btn\",\"rows\":237,\"data\":[{\"rank\":1,\"nickname\":\"Archi1\",\"points\":\"768.00\",\"prize\":\"40.00\"},{\"rank\":2,\"nickname\":\"Tuerrrr\",\"points\":\"760.00\",\"prize\":\"30.00\"},{\"rank\":3,\"nickname\":\"Fairy_Tale_\",\"points\":\"632.00\",\"prize\":\"24.00\"},{\"rank\":4,\"nickname\":\"p_a_r_a_d_o_x\",\"points\":\"583.00\",\"prize\":\"20.00\"},{\"rank\":5,\"nickname\":\"StaffOfMoses\",\"points\":\"567.00\",\"prize\":\"18.00\"},{\"rank\":6,\"nickname\":\"MT-POKER\",\"points\":\"563.00\",\"prize\":\"16.00\"},{\"rank\":7,\"nickname\":\"BaBadBaB\",\"points\":\"543.00\",\"prize\":\"14.00\"},{\"rank\":8,\"nickname\":\"inzuzo\",\"points\":\"531.00\",\"prize\":\"12.00\"},{\"rank\":9,\"nickname\":\"przz\",\"points\":\"501.00\",\"prize\":\"10.00\"},{\"rank\":10,\"nickname\":\"hwlm\",\"points\":\"460.00\",\"prize\":\"8.00\"},{\"rank\":11,\"nickname\":\"Andrylban\",\"points\":\"430.00\",\"prize\":\"7.00\"},{\"rank\":12,\"nickname\":\"angelass55\",\"points\":\"379.00\",\"prize\":\"6.00\"},{\"rank\":13,\"nickname\":\"CongBe\",\"points\":\"372.00\",\"prize\":\"5.00\"},{\"rank\":14,\"nickname\":\"readerq2\",\"points\":\"353.00\",\"prize\":\"5.00\"},{\"rank\":15,\"nickname\":\"Waip\",\"points\":\"352.00\",\"prize\":\"4.50\"},{\"rank\":16,\"nickname\":\"LiQUNXING\",\"points\":\"351.00\",\"prize\":\"4.50\"},{\"rank\":17,\"nickname\":\"Michael Hiraki\",\"points\":\"350.00\",\"prize\":\"4.50\"},{\"rank\":18,\"nickname\":\"makeboi\",\"points\":\"339.00\",\"prize\":\"4.00\"},{\"rank\":19,\"nickname\":\"baabaa32\",\"points\":\"336.00\",\"prize\":\"4.00\"},{\"rank\":20,\"nickname\":\"grudeman\",\"points\":\"311.00\",\"prize\":\"4.00\"},{\"rank\":21,\"nickname\":\"VelvetGuillotin\",\"points\":\"308.00\",\"prize\":\"4.00\"},{\"rank\":22,\"nickname\":\"yugimuto\",\"points\":\"306.00\",\"prize\":\"3.50\"},{\"rank\":23,\"nickname\":\"11AMVP11\",\"points\":\"297.00\",\"prize\":\"3.50\"},{\"rank\":24,\"nickname\":\"Marco Po1o\",\"points\":\"297.00\",\"prize\":\"3.00\"},{\"rank\":25,\"nickname\":\"PardeJotas\",\"points\":\"287.00\",\"prize\":\"3.00\"},{\"rank\":26,\"nickname\":\"v0Uset\",\"points\":\"277.00\",\"prize\":\"3.00\"},{\"rank\":27,\"nickname\":\"8iMiGH7Y8LUCK8\",\"points\":\"267.00\",\"prize\":\"3.00\"},{\"rank\":28,\"nickname\":\"GobigorGohom\",\"points\":\"261.00\",\"prize\":\"2.50\"},{\"rank\":29,\"nickname\":\"Isobet\",\"points\":\"253.00\",\"prize\":\"2.50\"},{\"rank\":30,\"nickname\":\"IamJoey\",\"points\":\"252.00\",\"prize\":\"2.50\"},{\"rank\":31,\"nickname\":\"Chovyyyyyyyy\",\"points\":\"248.00\",\"prize\":\"2.50\"},{\"rank\":32,\"nickname\":\"ICE Mendelson\",\"points\":\"239.00\",\"prize\":\"2.50\"},{\"rank\":33,\"nickname\":\"Totoxx93\",\"points\":\"237.00\",\"prize\":\"2.50\"},{\"rank\":34,\"nickname\":\"zFup\",\"points\":\"236.00\",\"prize\":\"2.50\"},{\"rank\":35,\"nickname\":\"116_ru\",\"points\":\"236.00\",\"prize\":\"2.00\"},{\"rank\":36,\"nickname\":\"principito25\",\"points\":\"235.00\",\"prize\":\"2.00\"},{\"rank\":37,\"nickname\":\"ANDRYWA\",\"points\":\"230.00\",\"prize\":\"2.00\"},{\"rank\":38,\"nickname\":\"One-GOG\",\"points\":\"226.00\",\"prize\":\"1.80\"},{\"rank\":39,\"nickname\":\"AleksFilimonov\",\"points\":\"224.00\",\"prize\":\"1.60\"},{\"rank\":40,\"nickname\":\"69Denis\",\"points\":\"221.00\",\"prize\":\"1.60\"},{\"rank\":41,\"nickname\":\"sicjoker\",\"points\":\"217.00\",\"prize\":\"1.40\"},{\"rank\":42,\"nickname\":\"Tesla396\",\"points\":\"217.00\",\"prize\":\"1.40\"},{\"rank\":43,\"nickname\":\"ploysarawut\",\"points\":\"206.00\",\"prize\":\"1.40\"},{\"rank\":44,\"nickname\":\"avesanta999\",\"points\":\"196.00\",\"prize\":\"1.40\"},{\"rank\":45,\"nickname\":\"disys\",\"points\":\"196.00\",\"prize\":\"1.40\"},{\"rank\":46,\"nickname\":\"willmart\",\"points\":\"195.00\",\"prize\":\"1.40\"},{\"rank\":47,\"nickname\":\"mtwd!d\",\"points\":\"193.00\",\"prize\":\"1.40\"},{\"rank\":48,\"nickname\":\"fightersol\",\"points\":\"190.00\",\"prize\":\"1.40\"},{\"rank\":49,\"nickname\":\"FoldToFear\",\"points\":\"188.00\",\"prize\":\"1.40\"},{\"rank\":50,\"nickname\":\"Yara1984\",\"points\":\"188.00\",\"prize\":\"1.40\"},{\"rank\":51,\"nickname\":\"Laguznyak\",\"points\":\"186.00\",\"prize\":\"1.20\"},{\"rank\":52,\"nickname\":\"Tobinja\",\"points\":\"184.00\",\"prize\":\"1.20\"},{\"rank\":53,\"nickname\":\"DayOneToday\",\"points\":\"183.00\",\"prize\":\"1.20\"},{\"rank\":54,\"nickname\":\"gezazeg\",\"points\":\"181.00\",\"prize\":\"1.20\"},{\"rank\":55,\"nickname\":\"Sherlok1295\",\"points\":\"181.00\",\"prize\":\"1.20\"},{\"rank\":56,\"nickname\":\"Spasibozadengi\",\"points\":\"180.00\",\"prize\":\"1.20\"},{\"rank\":57,\"nickname\":\"Eduard1789\",\"points\":\"179.00\",\"prize\":\"1.20\"},{\"rank\":58,\"nickname\":\"YmmR Vzla\",\"points\":\"175.00\",\"prize\":\"1.20\"},{\"rank\":59,\"nickname\":\"X@X@\",\"points\":\"174.00\",\"prize\":\"1.20\"},{\"rank\":60,\"nickname\":\"MAEDA ATSUKO\",\"points\":\"174.00\",\"prize\":\"1.20\"},{\"rank\":61,\"nickname\":\"xiaoer18\",\"points\":\"173.00\",\"prize\":\"1.00\"},{\"rank\":62,\"nickname\":\"Martine_o_poker\",\"points\":\"170.00\",\"prize\":\"1.00\"},{\"rank\":63,\"nickname\":\"m_ange04\",\"points\":\"168.00\",\"prize\":\"1.00\"},{\"rank\":64,\"nickname\":\"veldzk\",\"points\":\"168.00\",\"prize\":\"1.00\"},{\"rank\":65,\"nickname\":\"JavierSP\",\"points\":\"165.00\",\"prize\":\"1.00\"},{\"rank\":66,\"nickname\":\"De@lersingss\",\"points\":\"160.00\",\"prize\":\"1.00\"},{\"rank\":67,\"nickname\":\"Truszo\",\"points\":\"160.00\",\"prize\":\"1.00\"},{\"rank\":68,\"nickname\":\"Suriya Pattha\",\"points\":\"157.00\",\"prize\":\"1.00\"},{\"rank\":69,\"nickname\":\"Blackfeniks\",\"points\":\"156.00\",\"prize\":\"1.00\"},{\"rank\":70,\"nickname\":\"VODA\",\"points\":\"155.00\",\"prize\":\"1.00\"},{\"rank\":71,\"nickname\":\"kumapai\",\"points\":\"152.00\",\"prize\":\"0.80\"},{\"rank\":72,\"nickname\":\"Dragon Yu\",\"points\":\"151.00\",\"prize\":\"0.80\"},{\"rank\":73,\"nickname\":\"XKarsonX\",\"points\":\"150.00\",\"prize\":\"0.80\"},{\"rank\":74,\"nickname\":\"Danil Nagibator\",\"points\":\"149.00\",\"prize\":\"0.80\"},{\"rank\":75,\"nickname\":\"marcholi\",\"points\":\"148.00\",\"prize\":\"0.80\"},{\"rank\":76,\"nickname\":\"AngukaNayo\",\"points\":\"144.00\",\"prize\":\"0.80\"},{\"rank\":77,\"nickname\":\"suggest66\",\"points\":\"141.00\",\"prize\":\"0.80\"},{\"rank\":78,\"nickname\":\"kubarez\",\"points\":\"140.00\",\"prize\":\"0.80\"},{\"rank\":79,\"nickname\":\"Scarlett Ohara\",\"points\":\"138.00\",\"prize\":\"0.80\"},{\"rank\":80,\"nickname\":\"Calevala\",\"points\":\"137.00\",\"prize\":\"0.80\"},{\"rank\":81,\"nickname\":\"Admiral_Goodok\",\"points\":\"134.00\",\"prize\":\"0.80\"},{\"rank\":82,\"nickname\":\"stupid_bear1\",\"points\":\"133.00\",\"prize\":\"0.80\"},{\"rank\":83,\"nickname\":\"BigFly@\",\"points\":\"132.00\",\"prize\":\"0.80\"},{\"rank\":84,\"nickname\":\"PTJames\",\"points\":\"130.00\",\"prize\":\"0.80\"},{\"rank\":85,\"nickname\":\"arabbithole\",\"points\":\"128.00\",\"prize\":\"0.80\"},{\"rank\":86,\"nickname\":\"sharif2210\",\"points\":\"124.00\",\"prize\":\"0.80\"},{\"rank\":87,\"nickname\":\"Elots\",\"points\":\"123.00\",\"prize\":\"0.80\"},{\"rank\":88,\"nickname\":\"zhongguorenniu@\",\"points\":\"123.00\",\"prize\":\"0.80\"},{\"rank\":89,\"nickname\":\"Mariusz_kr1\",\"points\":\"121.00\",\"prize\":\"0.80\"},{\"rank\":90,\"nickname\":\"0X0TA\",\"points\":\"120.00\",\"prize\":\"0.80\"},{\"rank\":91,\"nickname\":\"DP-HHH\",\"points\":\"120.00\",\"prize\":\"0.60\"},{\"rank\":92,\"nickname\":\"OhLiGei\",\"points\":\"119.00\",\"prize\":\"0.60\"},{\"rank\":93,\"nickname\":\"RoyalKane\",\"points\":\"119.00\",\"prize\":\"0.60\"},{\"rank\":94,\"nickname\":\"DVsobaka\",\"points\":\"118.00\",\"prize\":\"0.60\"},{\"rank\":95,\"nickname\":\"I love pigeons\",\"points\":\"118.00\",\"prize\":\"0.60\"},{\"rank\":96,\"nickname\":\"AllIsFake\",\"points\":\"118.00\",\"prize\":\"0.60\"},{\"rank\":97,\"nickname\":\"Pavell445\",\"points\":\"118.00\",\"prize\":\"0.60\"},{\"rank\":98,\"nickname\":\"somidwey\",\"points\":\"117.00\",\"prize\":\"0.60\"},{\"rank\":99,\"nickname\":\"meeps\",\"points\":\"113.00\",\"prize\":\"0.60\"},{\"rank\":100,\"nickname\":\"ArchiBack\",\"points\":\"111.00\",\"prize\":\"0.60\"},{\"rank\":101,\"nickname\":\"Devilfish1209\",\"points\":\"111.00\",\"prize\":\"0.60\"},{\"rank\":102,\"nickname\":\"EriKKir\",\"points\":\"111.00\",\"prize\":\"0.60\"},{\"rank\":103,\"nickname\":\"TarzanBoy6\",\"points\":\"110.00\",\"prize\":\"0.60\"},{\"rank\":104,\"nickname\":\"DM21911\",\"points\":\"109.00\",\"prize\":\"0.60\"},{\"rank\":105,\"nickname\":\"Metal-Pescado\",\"points\":\"108.00\",\"prize\":\"0.60\"},{\"rank\":106,\"nickname\":\"krot72\",\"points\":\"106.00\",\"prize\":\"0.60\"},{\"rank\":107,\"nickname\":\"Hww66\",\"points\":\"106.00\",\"prize\":\"0.60\"},{\"rank\":108,\"nickname\":\"DUFeelLuckyPUNK\",\"points\":\"105.00\",\"prize\":\"0.60\"},{\"rank\":109,\"nickname\":\"Dzhabar\",\"points\":\"103.00\",\"prize\":\"0.60\"},{\"rank\":110,\"nickname\":\"traveljack\",\"points\":\"102.00\",\"prize\":\"0.60\"},{\"rank\":111,\"nickname\":\"aevo\",\"points\":\"101.00\",\"prize\":\"0.60\"},{\"rank\":112,\"nickname\":\"Skynew909\",\"points\":\"101.00\",\"prize\":\"0.60\"},{\"rank\":113,\"nickname\":\"KO]I[EMA\",\"points\":\"101.00\",\"prize\":\"0.60\"},{\"rank\":114,\"nickname\":\"1nside0ut\",\"points\":\"100.00\",\"prize\":\"0.60\"},{\"rank\":115,\"nickname\":\"Platon117\",\"points\":\"100.00\",\"prize\":\"0.60\"},{\"rank\":116,\"nickname\":\"MaiHong\",\"points\":\"100.00\",\"prize\":\"0.60\"},{\"rank\":117,\"nickname\":\"Exerman\",\"points\":\"100.00\",\"prize\":\"0.60\"},{\"rank\":118,\"nickname\":\"tropicante9\",\"points\":\"99.00\",\"prize\":\"0.60\"},{\"rank\":119,\"nickname\":\"diluzhen\",\"points\":\"99.00\",\"prize\":\"0.60\"},{\"rank\":120,\"nickname\":\"Lucky1188\",\"points\":\"99.00\",\"prize\":\"0.60\"},{\"rank\":121,\"nickname\":\"illi4\",\"points\":\"99.00\",\"prize\":\"0.60\"},{\"rank\":122,\"nickname\":\"PadreSnow\",\"points\":\"98.00\",\"prize\":\"0.60\"},{\"rank\":123,\"nickname\":\"P2807-6799\",\"points\":\"98.00\",\"prize\":\"0.60\"},{\"rank\":124,\"nickname\":\"t0b1as\",\"points\":\"98.00\",\"prize\":\"0.60\"},{\"rank\":125,\"nickname\":\"DsOne\",\"points\":\"97.00\",\"prize\":\"0.60\"},{\"rank\":126,\"nickname\":\"Shurigo\",\"points\":\"97.00\",\"prize\":\"0.60\"},{\"rank\":127,\"nickname\":\"parabel1um\",\"points\":\"97.00\",\"prize\":\"0.60\"},{\"rank\":128,\"nickname\":\"quopana\",\"points\":\"95.00\",\"prize\":\"0.60\"},{\"rank\":129,\"nickname\":\"oleban\",\"points\":\"95.00\",\"prize\":\"0.60\"},{\"rank\":130,\"nickname\":\"Spirovsk1y\",\"points\":\"95.00\",\"prize\":\"0.60\"},{\"rank\":131,\"nickname\":\"Antonizfrantsii\",\"points\":\"94.00\",\"prize\":\"0.40\"},{\"rank\":132,\"nickname\":\"Sitonzo\",\"points\":\"93.00\",\"prize\":\"0.40\"},{\"rank\":133,\"nickname\":\"Burrrrs\",\"points\":\"92.00\",\"prize\":\"0.40\"},{\"rank\":134,\"nickname\":\"HL554416\",\"points\":\"92.00\",\"prize\":\"0.40\"},{\"rank\":135,\"nickname\":\"vdima\",\"points\":\"92.00\",\"prize\":\"0.40\"},{\"rank\":136,\"nickname\":\"MUlric\",\"points\":\"91.00\",\"prize\":\"0.40\"},{\"rank\":137,\"nickname\":\"bingoxxxxxxx69\",\"points\":\"91.00\",\"prize\":\"0.40\"},{\"rank\":138,\"nickname\":\"gg_wallet\",\"points\":\"90.00\",\"prize\":\"0.40\"},{\"rank\":139,\"nickname\":\"RoadtoTmillion\",\"points\":\"89.00\",\"prize\":\"0.40\"},{\"rank\":140,\"nickname\":\"Lihotvor\",\"points\":\"89.00\",\"prize\":\"0.40\"},{\"rank\":141,\"nickname\":\"WhiteMag\",\"points\":\"89.00\",\"prize\":\"0.40\"},{\"rank\":142,\"nickname\":\"Chaos07\",\"points\":\"88.00\",\"prize\":\"0.40\"},{\"rank\":143,\"nickname\":\"OgBattousai\",\"points\":\"87.00\",\"prize\":\"0.40\"},{\"rank\":144,\"nickname\":\"Alexin34\",\"points\":\"86.00\",\"prize\":\"0.40\"},{\"rank\":145,\"nickname\":\"ombun\",\"points\":\"86.00\",\"prize\":\"0.40\"},{\"rank\":146,\"nickname\":\"mookhin\",\"points\":\"86.00\",\"prize\":\"0.40\"},{\"rank\":147,\"nickname\":\"Dxb24\",\"points\":\"86.00\",\"prize\":\"0.40\"},{\"rank\":148,\"nickname\":\"LexLuger\",\"points\":\"85.00\",\"prize\":\"0.40\"},{\"rank\":149,\"nickname\":\"grafo-man\",\"points\":\"84.00\",\"prize\":\"0.40\"},{\"rank\":150,\"nickname\":\"nanzval\",\"points\":\"84.00\",\"prize\":\"0.40\"},{\"rank\":151,\"nickname\":\"infinity lie\",\"points\":\"83.00\",\"prize\":\"0.40\"},{\"rank\":152,\"nickname\":\"Yetiii\",\"points\":\"83.00\",\"prize\":\"0.40\"},{\"rank\":153,\"nickname\":\"xiaoYYxiao\",\"points\":\"82.00\",\"prize\":\"0.40\"},{\"rank\":154,\"nickname\":\"Lakiz\",\"points\":\"82.00\",\"prize\":\"0.40\"},{\"rank\":155,\"nickname\":\"jose-demerzel\",\"points\":\"82.00\",\"prize\":\"0.40\"},{\"rank\":156,\"nickname\":\"Jimmytheshooter\",\"points\":\"81.00\",\"prize\":\"0.40\"},{\"rank\":157,\"nickname\":\"Bachateras\",\"points\":\"80.00\",\"prize\":\"0.40\"},{\"rank\":158,\"nickname\":\"hdjdkxk\",\"points\":\"80.00\",\"prize\":\"0.40\"},{\"rank\":159,\"nickname\":\"Bazilio-Vasily\",\"points\":\"80.00\",\"prize\":\"0.40\"},{\"rank\":160,\"nickname\":\"Francoboi\",\"points\":\"79.00\",\"prize\":\"0.40\"},{\"rank\":161,\"nickname\":\"confik\",\"points\":\"79.00\",\"prize\":\"0.40\"},{\"rank\":162,\"nickname\":\"Daniel Pozar\",\"points\":\"78.00\",\"prize\":\"0.40\"},{\"rank\":163,\"nickname\":\"Kavka77\",\"points\":\"77.00\",\"prize\":\"0.40\"},{\"rank\":164,\"nickname\":\"oofire\",\"points\":\"77.00\",\"prize\":\"0.40\"},{\"rank\":165,\"nickname\":\"reezels\",\"points\":\"76.00\",\"prize\":\"0.40\"},{\"rank\":166,\"nickname\":\"dudus1820\",\"points\":\"75.00\",\"prize\":\"0.40\"},{\"rank\":167,\"nickname\":\"SVSFK\",\"points\":\"74.00\",\"prize\":\"0.40\"},{\"rank\":168,\"nickname\":\"StepC\",\"points\":\"74.00\",\"prize\":\"0.40\"},{\"rank\":169,\"nickname\":\"klerul\",\"points\":\"74.00\",\"prize\":\"0.40\"},{\"rank\":170,\"nickname\":\"J4ck_p0t\",\"points\":\"74.00\",\"prize\":\"0.40\"},{\"rank\":171,\"nickname\":\"lulufa008\",\"points\":\"73.00\",\"prize\":\"0.20\"},{\"rank\":172,\"nickname\":\"Demarcation\",\"points\":\"73.00\",\"prize\":\"0.20\"},{\"rank\":173,\"nickname\":\"SPQR111\",\"points\":\"71.00\",\"prize\":\"0.20\"},{\"rank\":174,\"nickname\":\"Kentavr1k\",\"points\":\"70.00\",\"prize\":\"0.20\"},{\"rank\":175,\"nickname\":\"Attson\",\"points\":\"70.00\",\"prize\":\"0.20\"},{\"rank\":176,\"nickname\":\"Frokman\",\"points\":\"70.00\",\"prize\":\"0.20\"},{\"rank\":177,\"nickname\":\"DenVolchansk\",\"points\":\"70.00\",\"prize\":\"0.20\"},{\"rank\":178,\"nickname\":\"iqqqqqor\",\"points\":\"69.00\",\"prize\":\"0.20\"},{\"rank\":179,\"nickname\":\"Solo_Joker\",\"points\":\"69.00\",\"prize\":\"0.20\"},{\"rank\":180,\"nickname\":\"iamout\",\"points\":\"68.00\",\"prize\":\"0.20\"},{\"rank\":181,\"nickname\":\"maksmptof\",\"points\":\"68.00\",\"prize\":\"0.20\"},{\"rank\":182,\"nickname\":\"Crazy77777777\",\"points\":\"68.00\",\"prize\":\"0.20\"},{\"rank\":183,\"nickname\":\"WinniePoole\",\"points\":\"67.00\",\"prize\":\"0.20\"},{\"rank\":184,\"nickname\":\"GAME_OVER [-_-]\",\"points\":\"67.00\",\"prize\":\"0.20\"},{\"rank\":185,\"nickname\":\"dragoos\",\"points\":\"66.00\",\"prize\":\"0.20\"},{\"rank\":186,\"nickname\":\"H11YloveCh\",\"points\":\"66.00\",\"prize\":\"0.20\"},{\"rank\":187,\"nickname\":\"xKaiwingx\",\"points\":\"66.00\",\"prize\":\"0.20\"},{\"rank\":188,\"nickname\":\"Hammeringyon\",\"points\":\"66.00\",\"prize\":\"0.20\"},{\"rank\":189,\"nickname\":\"NO FOMO\",\"points\":\"65.00\",\"prize\":\"0.20\"},{\"rank\":190,\"nickname\":\"Ilari Vlasov\",\"points\":\"65.00\",\"prize\":\"0.20\"},{\"rank\":191,\"nickname\":\"V!C@\",\"points\":\"65.00\",\"prize\":\"0.20\"},{\"rank\":192,\"nickname\":\"Jetson\",\"points\":\"65.00\",\"prize\":\"0.20\"},{\"rank\":193,\"nickname\":\"ChickenBoyYy\",\"points\":\"64.00\",\"prize\":\"0.20\"},{\"rank\":194,\"nickname\":\"teletron1x\",\"points\":\"64.00\",\"prize\":\"0.20\"},{\"rank\":195,\"nickname\":\"DrTuube\",\"points\":\"64.00\",\"prize\":\"0.20\"},{\"rank\":196,\"nickname\":\"Krzemien9\",\"points\":\"64.00\",\"prize\":\"0.20\"},{\"rank\":197,\"nickname\":\"an_unknownv\",\"points\":\"63.00\",\"prize\":\"0.20\"},{\"rank\":198,\"nickname\":\"Krancher\",\"points\":\"63.00\",\"prize\":\"0.20\"},{\"rank\":199,\"nickname\":\"DavidGianG\",\"points\":\"62.00\",\"prize\":\"0.20\"},{\"rank\":200,\"nickname\":\"Kadiee\",\"points\":\"62.00\",\"prize\":\"0.20\"},{\"rank\":201,\"nickname\":\"Sttl1\",\"points\":\"62.00\",\"prize\":\"0.20\"},{\"rank\":202,\"nickname\":\"wuyihengliu\",\"points\":\"61.00\",\"prize\":\"0.20\"},{\"rank\":203,\"nickname\":\"futurewind\",\"points\":\"61.00\",\"prize\":\"0.20\"},{\"rank\":204,\"nickname\":\"HoHoCheng\",\"points\":\"61.00\",\"prize\":\"0.20\"},{\"rank\":205,\"nickname\":\"Screeam\",\"points\":\"61.00\",\"prize\":\"0.20\"},{\"rank\":206,\"nickname\":\"SMB88\",\"points\":\"61.00\",\"prize\":\"0.20\"},{\"rank\":207,\"nickname\":\"linxiao\",\"points\":\"60.00\",\"prize\":\"0.20\"},{\"rank\":208,\"nickname\":\"DanVoFloPopadan\",\"points\":\"60.00\",\"prize\":\"0.20\"},{\"rank\":209,\"nickname\":\"rrbrabo\",\"points\":\"60.00\",\"prize\":\"0.20\"},{\"rank\":210,\"nickname\":\"Yz52420\",\"points\":\"60.00\",\"prize\":\"0.20\"},{\"rank\":211,\"nickname\":\"hexer13\",\"points\":\"59.00\",\"prize\":\"0.20\"},{\"rank\":212,\"nickname\":\"Yender349\",\"points\":\"59.00\",\"prize\":\"0.20\"},{\"rank\":213,\"nickname\":\"Y-xiu\",\"points\":\"59.00\",\"prize\":\"0.20\"},{\"rank\":214,\"nickname\":\"0xygen\",\"points\":\"59.00\",\"prize\":\"0.20\"},{\"rank\":215,\"nickname\":\"CR7fun\",\"points\":\"57.00\",\"prize\":\"0.20\"},{\"rank\":216,\"nickname\":\"jacky7913\",\"points\":\"57.00\",\"prize\":\"0.20\"},{\"rank\":217,\"nickname\":\"jahjah89\",\"points\":\"57.00\",\"prize\":\"0.20\"},{\"rank\":218,\"nickname\":\"M123N\",\"points\":\"57.00\",\"prize\":\"0.20\"},{\"rank\":219,\"nickname\":\"THE END GAMER\",\"points\":\"57.00\",\"prize\":\"0.20\"},{\"rank\":220,\"nickname\":\"Mc007bond\",\"points\":\"57.00\",\"prize\":\"0.20\"},{\"rank\":221,\"nickname\":\"TheYoungShark\",\"points\":\"56.00\",\"prize\":\"0.20\"},{\"rank\":222,\"nickname\":\"poker ace 40\",\"points\":\"56.00\",\"prize\":\"0.20\"},{\"rank\":223,\"nickname\":\"Pavkin\",\"points\":\"56.00\",\"prize\":\"0.20\"},{\"rank\":224,\"nickname\":\"alph1997\",\"points\":\"56.00\",\"prize\":\"0.20\"},{\"rank\":225,\"nickname\":\"KIM0312\",\"points\":\"56.00\",\"prize\":\"0.20\"},{\"rank\":226,\"nickname\":\"JoroezZ\",\"points\":\"55.00\",\"prize\":\"0.20\"},{\"rank\":227,\"nickname\":\"iron Ruha\",\"points\":\"55.00\",\"prize\":\"0.20\"},{\"rank\":228,\"nickname\":\"ssggor\",\"points\":\"55.00\",\"prize\":\"0.20\"},{\"rank\":229,\"nickname\":\"dapygbhpyc\",\"points\":\"54.00\",\"prize\":\"0.20\"},{\"rank\":230,\"nickname\":\"fishdreamer\",\"points\":\"53.00\",\"prize\":\"0.20\"},{\"rank\":231,\"nickname\":\"Koto111\",\"points\":\"52.00\",\"prize\":\"0.20\"},{\"rank\":232,\"nickname\":\"CS_Bonsai\",\"points\":\"52.00\",\"prize\":\"0.20\"},{\"rank\":233,\"nickname\":\"DeadMagic\",\"points\":\"52.00\",\"prize\":\"0.20\"},{\"rank\":234,\"nickname\":\"Venzel24\",\"points\":\"52.00\",\"prize\":\"0.20\"},{\"rank\":235,\"nickname\":\"RFAK\",\"points\":\"51.00\",\"prize\":\"0.20\"},{\"rank\":236,\"nickname\":\"king12T\",\"points\":\"51.00\",\"prize\":\"0.20\"},{\"rank\":237,\"nickname\":\"Alberrrrt\",\"points\":\"51.00\",\"prize\":\"0.20\"}]}"
}