{
  "success": true,
  "result": "{\"stake\":\"nl50\",\"blinds\":\"$0.25/$0.50\",\"date\":\"2025-12-25\",\"dateText\":\"ui-btn\",\"rows\":268,\"data\":[{\"rank\":1,\"nickname\":\"wudalang\",\"points\":\"36081.00\",\"prize\":\"250.00\"},{\"rank\":2,\"nickname\":\"Fritzie\",\"points\":\"33679.00\",\"prize\":\"180.00\"},{\"rank\":3,\"nickname\":\"rknsmn\",\"points\":\"32036.00\",\"prize\":\"160.00\"},{\"rank\":4,\"nickname\":\"ncsHWncs\",\"points\":\"28993.00\",\"prize\":\"150.00\"},{\"rank\":5,\"nickname\":\"kaidiwang\",\"points\":\"27012.00\",\"prize\":\"140.00\"},{\"rank\":6,\"nickname\":\"lifish1\",\"points\":\"27010.00\",\"prize\":\"140.00\"},{\"rank\":7,\"nickname\":\"Melody@@\",\"points\":\"26274.00\",\"prize\":\"130.00\"},{\"rank\":8,\"nickname\":\"Mossad\",\"points\":\"25881.00\",\"prize\":\"130.00\"},{\"rank\":9,\"nickname\":\"myloveFbbj\",\"points\":\"25025.00\",\"prize\":\"120.00\"},{\"rank\":10,\"nickname\":\"Ankhes\",\"points\":\"24768.00\",\"prize\":\"120.00\"},{\"rank\":11,\"nickname\":\"fosjiytrr\",\"points\":\"23425.00\",\"prize\":\"100.00\"},{\"rank\":12,\"nickname\":\"xdks2510\",\"points\":\"22830.00\",\"prize\":\"80.00\"},{\"rank\":13,\"nickname\":\"LOGOSS\",\"points\":\"22257.00\",\"prize\":\"70.00\"},{\"rank\":14,\"nickname\":\"n0scete1psum\",\"points\":\"20828.00\",\"prize\":\"60.00\"},{\"rank\":15,\"nickname\":\"yAngYu P\",\"points\":\"20773.00\",\"prize\":\"50.00\"},{\"rank\":16,\"nickname\":\"Control calm\",\"points\":\"20324.00\",\"prize\":\"40.00\"},{\"rank\":17,\"nickname\":\"shrimp-TY\",\"points\":\"19661.00\",\"prize\":\"30.00\"},{\"rank\":18,\"nickname\":\"Easypokeriiii\",\"points\":\"18401.00\",\"prize\":\"30.00\"},{\"rank\":19,\"nickname\":\"shelven0123\",\"points\":\"17125.00\",\"prize\":\"30.00\"},{\"rank\":20,\"nickname\":\"3out_badbeat\",\"points\":\"16240.00\",\"prize\":\"30.00\"},{\"rank\":21,\"nickname\":\"super00998178\",\"points\":\"15489.00\",\"prize\":\"30.00\"},{\"rank\":22,\"nickname\":\"yiyore\",\"points\":\"15105.00\",\"prize\":\"30.00\"},{\"rank\":23,\"nickname\":\"nobody321\",\"points\":\"14889.00\",\"prize\":\"30.00\"},{\"rank\":24,\"nickname\":\"gogo-tang\",\"points\":\"14497.00\",\"prize\":\"30.00\"},{\"rank\":25,\"nickname\":\"DUDURRRAK47\",\"points\":\"14121.00\",\"prize\":\"30.00\"},{\"rank\":26,\"nickname\":\"Jiangpoker\",\"points\":\"14082.00\",\"prize\":\"30.00\"},{\"rank\":27,\"nickname\":\"Miaacue\",\"points\":\"13739.00\",\"prize\":\"20.00\"},{\"rank\":28,\"nickname\":\"Qu1ckS1lv3rZAOL\",\"points\":\"13456.00\",\"prize\":\"20.00\"},{\"rank\":29,\"nickname\":\"Han_Tianzun\",\"points\":\"12703.00\",\"prize\":\"20.00\"},{\"rank\":30,\"nickname\":\"Cho2ee\",\"points\":\"12467.00\",\"prize\":\"20.00\"},{\"rank\":31,\"nickname\":\"Gshanhunter\",\"points\":\"12098.00\",\"prize\":\"20.00\"},{\"rank\":32,\"nickname\":\"o6F2nZ0vQ\",\"points\":\"11574.00\",\"prize\":\"20.00\"},{\"rank\":33,\"nickname\":\"PGPowehi\",\"points\":\"11196.00\",\"prize\":\"20.00\"},{\"rank\":34,\"nickname\":\"Panda Man 0310\",\"points\":\"11196.00\",\"prize\":\"20.00\"},{\"rank\":35,\"nickname\":\"NoGameNoSkill\",\"points\":\"10947.00\",\"prize\":\"20.00\"},{\"rank\":36,\"nickname\":\"MarquesAdv\",\"points\":\"10664.00\",\"prize\":\"20.00\"},{\"rank\":38,\"nickname\":\"knife2017\",\"points\":\"10584.00\",\"prize\":\"20.00\"},{\"rank\":39,\"nickname\":\"Liii\",\"points\":\"10315.00\",\"prize\":\"20.00\"},{\"rank\":40,\"nickname\":\"Sky-xiayu\",\"points\":\"10276.00\",\"prize\":\"20.00\"},{\"rank\":41,\"nickname\":\"ShPokerKing79\",\"points\":\"10238.00\",\"prize\":\"15.00\"},{\"rank\":42,\"nickname\":\"P3854-3660\",\"points\":\"10134.00\",\"prize\":\"15.00\"},{\"rank\":43,\"nickname\":\"MateeCocido\",\"points\":\"10050.00\",\"prize\":\"15.00\"},{\"rank\":44,\"nickname\":\"OslikUA_Love\",\"points\":\"10045.00\",\"prize\":\"15.00\"},{\"rank\":45,\"nickname\":\"User-K72\",\"points\":\"10035.00\",\"prize\":\"15.00\"},{\"rank\":46,\"nickname\":\"LootNRun\",\"points\":\"9780.00\",\"prize\":\"15.00\"},{\"rank\":47,\"nickname\":\"ezlol\",\"points\":\"9732.00\",\"prize\":\"15.00\"},{\"rank\":48,\"nickname\":\"Omnibuss\",\"points\":\"9485.00\",\"prize\":\"15.00\"},{\"rank\":49,\"nickname\":\"Mike Coffee\",\"points\":\"9482.00\",\"prize\":\"15.00\"},{\"rank\":50,\"nickname\":\"LAMBRO0199\",\"points\":\"9305.00\",\"prize\":\"15.00\"},{\"rank\":51,\"nickname\":\"r4idenN\",\"points\":\"9279.00\",\"prize\":\"15.00\"},{\"rank\":52,\"nickname\":\"Mariocaru\",\"points\":\"9104.00\",\"prize\":\"15.00\"},{\"rank\":53,\"nickname\":\"Smarvinboy777\",\"points\":\"8722.00\",\"prize\":\"15.00\"},{\"rank\":54,\"nickname\":\"pigzzz\",\"points\":\"8487.00\",\"prize\":\"15.00\"},{\"rank\":55,\"nickname\":\"CLYA\",\"points\":\"8449.00\",\"prize\":\"15.00\"},{\"rank\":56,\"nickname\":\"lucky1897\",\"points\":\"8307.00\",\"prize\":\"15.00\"},{\"rank\":57,\"nickname\":\"orange-!\",\"points\":\"8067.00\",\"prize\":\"15.00\"},{\"rank\":58,\"nickname\":\"Zhzh88\",\"points\":\"8065.00\",\"prize\":\"15.00\"},{\"rank\":59,\"nickname\":\"Neverfo1d\",\"points\":\"8013.00\",\"prize\":\"15.00\"},{\"rank\":60,\"nickname\":\"Wanningboys\",\"points\":\"7982.00\",\"prize\":\"15.00\"},{\"rank\":61,\"nickname\":\"E_TrasH\",\"points\":\"7898.00\",\"prize\":\"15.00\"},{\"rank\":62,\"nickname\":\"nanako1989\",\"points\":\"7856.00\",\"prize\":\"15.00\"},{\"rank\":63,\"nickname\":\"River-jiang\",\"points\":\"7784.00\",\"prize\":\"15.00\"},{\"rank\":64,\"nickname\":\"ALEXALEXYXUNG\",\"points\":\"7695.00\",\"prize\":\"15.00\"},{\"rank\":65,\"nickname\":\"kei2000\",\"points\":\"7677.00\",\"prize\":\"15.00\"},{\"rank\":66,\"nickname\":\"LGG888\",\"points\":\"7643.00\",\"prize\":\"15.00\"},{\"rank\":67,\"nickname\":\"Moreallin\",\"points\":\"7572.00\",\"prize\":\"15.00\"},{\"rank\":68,\"nickname\":\"Enslaver\",\"points\":\"7515.00\",\"prize\":\"15.00\"},{\"rank\":69,\"nickname\":\"GoodOldMan\",\"points\":\"7400.00\",\"prize\":\"15.00\"},{\"rank\":70,\"nickname\":\"FreeYB\",\"points\":\"7249.00\",\"prize\":\"15.00\"},{\"rank\":71,\"nickname\":\"Jsmith\",\"points\":\"7135.00\",\"prize\":\"15.00\"},{\"rank\":72,\"nickname\":\"CCTV9\",\"points\":\"7097.00\",\"prize\":\"15.00\"},{\"rank\":73,\"nickname\":\"Milka95\",\"points\":\"7086.00\",\"prize\":\"15.00\"},{\"rank\":74,\"nickname\":\"99NeverLose\",\"points\":\"7057.00\",\"prize\":\"15.00\"},{\"rank\":75,\"nickname\":\"SB2501\",\"points\":\"6960.00\",\"prize\":\"15.00\"},{\"rank\":76,\"nickname\":\"Tommm boy\",\"points\":\"6942.00\",\"prize\":\"15.00\"},{\"rank\":77,\"nickname\":\"IBA1\",\"points\":\"6869.00\",\"prize\":\"15.00\"},{\"rank\":78,\"nickname\":\"Jack Zhanghx\",\"points\":\"6855.00\",\"prize\":\"15.00\"},{\"rank\":79,\"nickname\":\"fish_Henry\",\"points\":\"6786.00\",\"prize\":\"15.00\"},{\"rank\":81,\"nickname\":\"FuSSion\",\"points\":\"6653.00\",\"prize\":\"15.00\"},{\"rank\":82,\"nickname\":\"Afinaa\",\"points\":\"6549.00\",\"prize\":\"15.00\"},{\"rank\":83,\"nickname\":\"God_bless you\",\"points\":\"6306.00\",\"prize\":\"15.00\"},{\"rank\":84,\"nickname\":\"LosingDay\",\"points\":\"6204.00\",\"prize\":\"15.00\"},{\"rank\":85,\"nickname\":\"Kinsss\",\"points\":\"6180.00\",\"prize\":\"15.00\"},{\"rank\":86,\"nickname\":\"x-m8\",\"points\":\"6138.00\",\"prize\":\"15.00\"},{\"rank\":87,\"nickname\":\"bengdeng668\",\"points\":\"6086.00\",\"prize\":\"15.00\"},{\"rank\":88,\"nickname\":\"PinkDolphinx333\",\"points\":\"6083.00\",\"prize\":\"15.00\"},{\"rank\":89,\"nickname\":\"XJZZ007\",\"points\":\"6003.00\",\"prize\":\"15.00\"},{\"rank\":90,\"nickname\":\"taki2ydman\",\"points\":\"5994.00\",\"prize\":\"15.00\"},{\"rank\":91,\"nickname\":\"FwwFww\",\"points\":\"5976.00\",\"prize\":\"15.00\"},{\"rank\":92,\"nickname\":\"michtheo\",\"points\":\"5862.00\",\"prize\":\"15.00\"},{\"rank\":93,\"nickname\":\"tony1671\",\"points\":\"5850.00\",\"prize\":\"15.00\"},{\"rank\":94,\"nickname\":\"Chefxxx\",\"points\":\"5805.00\",\"prize\":\"15.00\"},{\"rank\":95,\"nickname\":\"SumFelix\",\"points\":\"5794.00\",\"prize\":\"15.00\"},{\"rank\":96,\"nickname\":\"samuel01121\",\"points\":\"5784.00\",\"prize\":\"15.00\"},{\"rank\":97,\"nickname\":\"gaaary\",\"points\":\"5754.00\",\"prize\":\"15.00\"},{\"rank\":98,\"nickname\":\"CyberTony\",\"points\":\"5720.00\",\"prize\":\"15.00\"},{\"rank\":99,\"nickname\":\"AAnimal\",\"points\":\"5689.00\",\"prize\":\"15.00\"},{\"rank\":100,\"nickname\":\"KATSP45\",\"points\":\"5669.00\",\"prize\":\"15.00\"},{\"rank\":101,\"nickname\":\"enot194\",\"points\":\"5666.00\",\"prize\":\"15.00\"},{\"rank\":102,\"nickname\":\"YJ-u2yw1\",\"points\":\"5612.00\",\"prize\":\"15.00\"},{\"rank\":103,\"nickname\":\"ki19\",\"points\":\"5601.00\",\"prize\":\"15.00\"},{\"rank\":104,\"nickname\":\"IronAwj\",\"points\":\"5508.00\",\"prize\":\"15.00\"},{\"rank\":105,\"nickname\":\"ckhaoyun\",\"points\":\"5452.00\",\"prize\":\"15.00\"},{\"rank\":106,\"nickname\":\"XINXINZX\",\"points\":\"5416.00\",\"prize\":\"15.00\"},{\"rank\":107,\"nickname\":\"Carrier_\",\"points\":\"5414.00\",\"prize\":\"15.00\"},{\"rank\":108,\"nickname\":\"Sandabal\",\"points\":\"5358.00\",\"prize\":\"15.00\"},{\"rank\":109,\"nickname\":\"Mad Super Mario\",\"points\":\"5338.00\",\"prize\":\"15.00\"},{\"rank\":110,\"nickname\":\"longyang\",\"points\":\"5336.00\",\"prize\":\"15.00\"},{\"rank\":111,\"nickname\":\"china-fishy\",\"points\":\"5335.00\",\"prize\":\"15.00\"},{\"rank\":112,\"nickname\":\"Nadezhda78\",\"points\":\"5290.00\",\"prize\":\"15.00\"},{\"rank\":113,\"nickname\":\"BetMeOut\",\"points\":\"5249.00\",\"prize\":\"15.00\"},{\"rank\":114,\"nickname\":\"Mrhiphop07\",\"points\":\"5225.00\",\"prize\":\"15.00\"},{\"rank\":115,\"nickname\":\"foxnic7777\",\"points\":\"5208.00\",\"prize\":\"15.00\"},{\"rank\":116,\"nickname\":\"Maliciouss\",\"points\":\"5195.00\",\"prize\":\"15.00\"},{\"rank\":117,\"nickname\":\"Kebabshopowner\",\"points\":\"5180.00\",\"prize\":\"15.00\"},{\"rank\":118,\"nickname\":\"Ofek_Edri\",\"points\":\"5155.00\",\"prize\":\"15.00\"},{\"rank\":119,\"nickname\":\"nomemory\",\"points\":\"5143.00\",\"prize\":\"15.00\"},{\"rank\":120,\"nickname\":\"StatuSG\",\"points\":\"5139.00\",\"prize\":\"15.00\"},{\"rank\":121,\"nickname\":\"BrotherSpray\",\"points\":\"5124.00\",\"prize\":\"15.00\"},{\"rank\":122,\"nickname\":\"suhhhh\",\"points\":\"5099.00\",\"prize\":\"15.00\"},{\"rank\":123,\"nickname\":\"Pybak\",\"points\":\"5089.00\",\"prize\":\"15.00\"},{\"rank\":124,\"nickname\":\"mengardinha\",\"points\":\"5052.00\",\"prize\":\"15.00\"},{\"rank\":125,\"nickname\":\"HoudiniV8\",\"points\":\"5038.00\",\"prize\":\"15.00\"},{\"rank\":126,\"nickname\":\"Alinoe\",\"points\":\"4974.00\",\"prize\":\"15.00\"},{\"rank\":127,\"nickname\":\"Mandinga1987\",\"points\":\"4957.00\",\"prize\":\"15.00\"},{\"rank\":128,\"nickname\":\"RiverRatKing\",\"points\":\"4926.00\",\"prize\":\"15.00\"},{\"rank\":129,\"nickname\":\"Belailija\",\"points\":\"4884.00\",\"prize\":\"15.00\"},{\"rank\":130,\"nickname\":\"RiverPlusEv\",\"points\":\"4870.00\",\"prize\":\"15.00\"},{\"rank\":131,\"nickname\":\"7betfold\",\"points\":\"4865.00\",\"prize\":\"15.00\"},{\"rank\":132,\"nickname\":\"alexhood\",\"points\":\"4853.00\",\"prize\":\"15.00\"},{\"rank\":133,\"nickname\":\"donjyo10\",\"points\":\"4840.00\",\"prize\":\"15.00\"},{\"rank\":134,\"nickname\":\"ohmyboxgod\",\"points\":\"4824.00\",\"prize\":\"15.00\"},{\"rank\":135,\"nickname\":\"gounvren\",\"points\":\"4788.00\",\"prize\":\"15.00\"},{\"rank\":136,\"nickname\":\"Alanngo\",\"points\":\"4784.00\",\"prize\":\"15.00\"},{\"rank\":137,\"nickname\":\"salladhor\",\"points\":\"4757.00\",\"prize\":\"15.00\"},{\"rank\":138,\"nickname\":\"lazyAby\",\"points\":\"4717.00\",\"prize\":\"15.00\"},{\"rank\":139,\"nickname\":\"P0kerd0ss1\",\"points\":\"4700.00\",\"prize\":\"15.00\"},{\"rank\":140,\"nickname\":\"JacksonDDD\",\"points\":\"4671.00\",\"prize\":\"15.00\"},{\"rank\":141,\"nickname\":\"BigBiangZzzzzz\",\"points\":\"4668.00\",\"prize\":\"15.00\"},{\"rank\":142,\"nickname\":\"3ence\",\"points\":\"4663.00\",\"prize\":\"15.00\"},{\"rank\":143,\"nickname\":\"Lucyluck888\",\"points\":\"4648.00\",\"prize\":\"15.00\"},{\"rank\":144,\"nickname\":\"Zemelya\",\"points\":\"4642.00\",\"prize\":\"15.00\"},{\"rank\":145,\"nickname\":\"BBZKK\",\"points\":\"4631.00\",\"prize\":\"15.00\"},{\"rank\":146,\"nickname\":\"anti gto\",\"points\":\"4612.00\",\"prize\":\"15.00\"},{\"rank\":147,\"nickname\":\"sky0729\",\"points\":\"4605.00\",\"prize\":\"15.00\"},{\"rank\":148,\"nickname\":\"zhangqqq\",\"points\":\"4581.00\",\"prize\":\"15.00\"},{\"rank\":149,\"nickname\":\"Louisiane\",\"points\":\"4571.00\",\"prize\":\"15.00\"},{\"rank\":150,\"nickname\":\"Pay0990\",\"points\":\"4532.00\",\"prize\":\"15.00\"},{\"rank\":151,\"nickname\":\"Jadeenthusiasts\",\"points\":\"4528.00\",\"prize\":\"15.00\"},{\"rank\":152,\"nickname\":\"Insane133\",\"points\":\"4519.00\",\"prize\":\"15.00\"},{\"rank\":153,\"nickname\":\"FuckBB\",\"points\":\"4518.00\",\"prize\":\"15.00\"},{\"rank\":154,\"nickname\":\"nosleep02\",\"points\":\"4505.00\",\"prize\":\"15.00\"},{\"rank\":155,\"nickname\":\"BerrrNanKeee\",\"points\":\"4482.00\",\"prize\":\"15.00\"},{\"rank\":156,\"nickname\":\"IceGoesNuts\",\"points\":\"4476.00\",\"prize\":\"15.00\"},{\"rank\":157,\"nickname\":\"BreezyPoker\",\"points\":\"4406.00\",\"prize\":\"15.00\"},{\"rank\":158,\"nickname\":\"Thepokerwhale\",\"points\":\"4379.00\",\"prize\":\"15.00\"},{\"rank\":159,\"nickname\":\"Jianggg\",\"points\":\"4376.00\",\"prize\":\"15.00\"},{\"rank\":160,\"nickname\":\"Drannek\",\"points\":\"4319.00\",\"prize\":\"15.00\"},{\"rank\":161,\"nickname\":\"Yuriy Ivanov\",\"points\":\"4313.00\",\"prize\":\"15.00\"},{\"rank\":162,\"nickname\":\"TG07\",\"points\":\"4312.00\",\"prize\":\"15.00\"},{\"rank\":163,\"nickname\":\"Akunflower\",\"points\":\"4309.00\",\"prize\":\"15.00\"},{\"rank\":164,\"nickname\":\"PotWhale\",\"points\":\"4306.00\",\"prize\":\"15.00\"},{\"rank\":165,\"nickname\":\"Alalalalong\",\"points\":\"4286.00\",\"prize\":\"15.00\"},{\"rank\":166,\"nickname\":\"J_Dianda\",\"points\":\"4282.00\",\"prize\":\"15.00\"},{\"rank\":167,\"nickname\":\"SaSaMaxPainSaSa\",\"points\":\"4277.00\",\"prize\":\"15.00\"},{\"rank\":168,\"nickname\":\"peterrrt\",\"points\":\"4269.00\",\"prize\":\"15.00\"},{\"rank\":169,\"nickname\":\"joaocanella\",\"points\":\"4251.00\",\"prize\":\"15.00\"},{\"rank\":170,\"nickname\":\"not bluff!\",\"points\":\"4237.00\",\"prize\":\"15.00\"},{\"rank\":171,\"nickname\":\"mazak89\",\"points\":\"4228.00\",\"prize\":\"15.00\"},{\"rank\":172,\"nickname\":\"UuuuuuuupSwing\",\"points\":\"4225.00\",\"prize\":\"15.00\"},{\"rank\":173,\"nickname\":\"Xuzi_pokerX\",\"points\":\"4221.00\",\"prize\":\"15.00\"},{\"rank\":174,\"nickname\":\"Firess\",\"points\":\"4219.00\",\"prize\":\"15.00\"},{\"rank\":175,\"nickname\":\"Oscar233\",\"points\":\"4219.00\",\"prize\":\"15.00\"},{\"rank\":176,\"nickname\":\"hackmane\",\"points\":\"4215.00\",\"prize\":\"15.00\"},{\"rank\":177,\"nickname\":\"Ablaze!\",\"points\":\"4208.00\",\"prize\":\"15.00\"},{\"rank\":178,\"nickname\":\"YANG LlU\",\"points\":\"4206.00\",\"prize\":\"15.00\"},{\"rank\":179,\"nickname\":\"mute all chat\",\"points\":\"4177.00\",\"prize\":\"15.00\"},{\"rank\":180,\"nickname\":\"LeGi4\",\"points\":\"4167.00\",\"prize\":\"15.00\"},{\"rank\":181,\"nickname\":\"Dmitrii Vitugin\",\"points\":\"4165.00\",\"prize\":\"15.00\"},{\"rank\":182,\"nickname\":\"SchrodingerCats\",\"points\":\"4163.00\",\"prize\":\"15.00\"},{\"rank\":183,\"nickname\":\"sailor-moon\",\"points\":\"4149.00\",\"prize\":\"15.00\"},{\"rank\":184,\"nickname\":\"pokerchive\",\"points\":\"4144.00\",\"prize\":\"15.00\"},{\"rank\":185,\"nickname\":\"hahaha31\",\"points\":\"4127.00\",\"prize\":\"15.00\"},{\"rank\":186,\"nickname\":\"chencer\",\"points\":\"4117.00\",\"prize\":\"15.00\"},{\"rank\":187,\"nickname\":\"boney999\",\"points\":\"4112.00\",\"prize\":\"15.00\"},{\"rank\":188,\"nickname\":\"Voroba42\",\"points\":\"4101.00\",\"prize\":\"15.00\"},{\"rank\":189,\"nickname\":\"yiqiehaihao\",\"points\":\"4081.00\",\"prize\":\"15.00\"},{\"rank\":190,\"nickname\":\"Emeryt\",\"points\":\"4079.00\",\"prize\":\"15.00\"},{\"rank\":191,\"nickname\":\"Volirs\",\"points\":\"4071.00\",\"prize\":\"15.00\"},{\"rank\":192,\"nickname\":\"balabalab\",\"points\":\"4068.00\",\"prize\":\"15.00\"},{\"rank\":193,\"nickname\":\"Kinbug\",\"points\":\"4063.00\",\"prize\":\"15.00\"},{\"rank\":194,\"nickname\":\"SoloLeveling888\",\"points\":\"3990.00\",\"prize\":\"15.00\"},{\"rank\":195,\"nickname\":\"speed-1\",\"points\":\"3946.00\",\"prize\":\"15.00\"},{\"rank\":196,\"nickname\":\"Lockerl7199\",\"points\":\"3922.00\",\"prize\":\"15.00\"},{\"rank\":197,\"nickname\":\"naterne\",\"points\":\"3921.00\",\"prize\":\"15.00\"},{\"rank\":198,\"nickname\":\"yasuom\",\"points\":\"3914.00\",\"prize\":\"15.00\"},{\"rank\":199,\"nickname\":\"fuleyou\",\"points\":\"3908.00\",\"prize\":\"15.00\"},{\"rank\":200,\"nickname\":\"GavCat3000\",\"points\":\"3902.00\",\"prize\":\"15.00\"},{\"rank\":201,\"nickname\":\"grumpig\",\"points\":\"3898.00\",\"prize\":\"15.00\"},{\"rank\":202,\"nickname\":\"Tuzin Ivan\",\"points\":\"3890.00\",\"prize\":\"15.00\"},{\"rank\":203,\"nickname\":\"Donk biubiu JP\",\"points\":\"3881.00\",\"prize\":\"15.00\"},{\"rank\":204,\"nickname\":\"Crazy Pig7\",\"points\":\"3875.00\",\"prize\":\"15.00\"},{\"rank\":205,\"nickname\":\"psychokiller86\",\"points\":\"3874.00\",\"prize\":\"15.00\"},{\"rank\":206,\"nickname\":\"mamu116\",\"points\":\"3873.00\",\"prize\":\"15.00\"},{\"rank\":207,\"nickname\":\"JonesJannik\",\"points\":\"3864.00\",\"prize\":\"15.00\"},{\"rank\":208,\"nickname\":\"xiaohsuan777\",\"points\":\"3856.00\",\"prize\":\"15.00\"},{\"rank\":209,\"nickname\":\"Winnetu\",\"points\":\"3854.00\",\"prize\":\"15.00\"},{\"rank\":210,\"nickname\":\"kuromi666\",\"points\":\"3845.00\",\"prize\":\"15.00\"},{\"rank\":211,\"nickname\":\"venveess\",\"points\":\"3834.00\",\"prize\":\"15.00\"},{\"rank\":212,\"nickname\":\"ShoTamPoBabkam\",\"points\":\"3823.00\",\"prize\":\"15.00\"},{\"rank\":213,\"nickname\":\"wakefulcheong\",\"points\":\"3821.00\",\"prize\":\"15.00\"},{\"rank\":214,\"nickname\":\"koda513\",\"points\":\"3818.00\",\"prize\":\"15.00\"},{\"rank\":215,\"nickname\":\"lost2am\",\"points\":\"3810.00\",\"prize\":\"15.00\"},{\"rank\":216,\"nickname\":\"Nuyoah_8\",\"points\":\"3776.00\",\"prize\":\"15.00\"},{\"rank\":217,\"nickname\":\"3xcellentGTO\",\"points\":\"3754.00\",\"prize\":\"15.00\"},{\"rank\":218,\"nickname\":\"UppercutDelux\",\"points\":\"3748.00\",\"prize\":\"15.00\"},{\"rank\":219,\"nickname\":\"zhuguanghushou\",\"points\":\"3740.00\",\"prize\":\"15.00\"},{\"rank\":220,\"nickname\":\"Jacomber\",\"points\":\"3728.00\",\"prize\":\"15.00\"},{\"rank\":221,\"nickname\":\"stuinscarlet\",\"points\":\"3725.00\",\"prize\":\"15.00\"},{\"rank\":222,\"nickname\":\"nzap\",\"points\":\"3717.00\",\"prize\":\"15.00\"},{\"rank\":223,\"nickname\":\"lively28\",\"points\":\"3708.00\",\"prize\":\"15.00\"},{\"rank\":224,\"nickname\":\"rara66\",\"points\":\"3707.00\",\"prize\":\"15.00\"},{\"rank\":225,\"nickname\":\"Autobott\",\"points\":\"3705.00\",\"prize\":\"15.00\"},{\"rank\":226,\"nickname\":\"CZZ3\",\"points\":\"3702.00\",\"prize\":\"15.00\"},{\"rank\":227,\"nickname\":\"St0ckfish\",\"points\":\"3702.00\",\"prize\":\"15.00\"},{\"rank\":228,\"nickname\":\"JaroszX\",\"points\":\"3694.00\",\"prize\":\"15.00\"},{\"rank\":229,\"nickname\":\"SupernovaAAAAAA\",\"points\":\"3679.00\",\"prize\":\"15.00\"},{\"rank\":230,\"nickname\":\"All-inLAD\",\"points\":\"3673.00\",\"prize\":\"15.00\"},{\"rank\":231,\"nickname\":\"Shhhhh\",\"points\":\"3658.00\",\"prize\":\"15.00\"},{\"rank\":232,\"nickname\":\"Kent300\",\"points\":\"3630.00\",\"prize\":\"15.00\"},{\"rank\":233,\"nickname\":\"SuperRobotWarY\",\"points\":\"3620.00\",\"prize\":\"15.00\"},{\"rank\":234,\"nickname\":\"Gadiaboy\",\"points\":\"3618.00\",\"prize\":\"15.00\"},{\"rank\":235,\"nickname\":\"BelieveSsS\",\"points\":\"3606.00\",\"prize\":\"15.00\"},{\"rank\":236,\"nickname\":\"sylj\",\"points\":\"3594.00\",\"prize\":\"15.00\"},{\"rank\":237,\"nickname\":\"IlIlIIlIIlIlIll\",\"points\":\"3593.00\",\"prize\":\"15.00\"},{\"rank\":238,\"nickname\":\"ZANOSZ\",\"points\":\"3583.00\",\"prize\":\"15.00\"},{\"rank\":239,\"nickname\":\"NAES1\",\"points\":\"3572.00\",\"prize\":\"15.00\"},{\"rank\":240,\"nickname\":\"Gus23\",\"points\":\"3556.00\",\"prize\":\"15.00\"},{\"rank\":241,\"nickname\":\"A1C3A1B2LEGIA\",\"points\":\"3540.00\",\"prize\":\"\"},{\"rank\":242,\"nickname\":\"QiaoBZ\",\"points\":\"3522.00\",\"prize\":\"\"},{\"rank\":243,\"nickname\":\"KonstantinD\",\"points\":\"3488.00\",\"prize\":\"\"},{\"rank\":244,\"nickname\":\"Karyudon\",\"points\":\"3487.00\",\"prize\":\"\"},{\"rank\":245,\"nickname\":\"FERMER1167\",\"points\":\"3487.00\",\"prize\":\"\"},{\"rank\":246,\"nickname\":\"leiminmin\",\"points\":\"3422.00\",\"prize\":\"\"},{\"rank\":247,\"nickname\":\"ChengZeXu\",\"points\":\"3392.00\",\"prize\":\"\"},{\"rank\":248,\"nickname\":\"PeTer888888888\",\"points\":\"3374.00\",\"prize\":\"\"},{\"rank\":249,\"nickname\":\"Allenhjz\",\"points\":\"3359.00\",\"prize\":\"\"},{\"rank\":250,\"nickname\":\"Xardix\",\"points\":\"3354.00\",\"prize\":\"\"},{\"rank\":251,\"nickname\":\"1ll1ll1\",\"points\":\"3347.00\",\"prize\":\"\"},{\"rank\":252,\"nickname\":\"michalemix88\",\"points\":\"3340.00\",\"prize\":\"\"},{\"rank\":253,\"nickname\":\"KarinaYu\",\"points\":\"3334.00\",\"prize\":\"\"},{\"rank\":254,\"nickname\":\"TheCrazyMonkey\",\"points\":\"3324.00\",\"prize\":\"\"},{\"rank\":255,\"nickname\":\"lulululuxw\",\"points\":\"3316.00\",\"prize\":\"\"},{\"rank\":256,\"nickname\":\"KenkoVN\",\"points\":\"3314.00\",\"prize\":\"\"},{\"rank\":257,\"nickname\":\"Ranofix1408\",\"points\":\"3285.00\",\"prize\":\"\"},{\"rank\":258,\"nickname\":\"YuanBao Papa\",\"points\":\"3274.00\",\"prize\":\"\"},{\"rank\":259,\"nickname\":\"Cerberus210\",\"points\":\"3189.00\",\"prize\":\"\"},{\"rank\":260,\"nickname\":\"owen33\",\"points\":\"3180.00\",\"prize\":\"\"},{\"rank\":261,\"nickname\":\"fishgggs\",\"points\":\"3167.00\",\"prize\":\"\"},{\"rank\":262,\"nickname\":\"Biana Zana\",\"points\":\"3161.00\",\"prize\":\"\"},{\"rank\":263,\"nickname\":\"dashaoyu\",\"points\":\"3126.00\",\"prize\":\"\"},{\"rank\":264,\"nickname\":\"Shut_aP\",\"points\":\"3088.00\",\"prize\":\"\"},{\"rank\":265,\"nickname\":\"I Yastremskyi\",\"points\":\"3088.00\",\"prize\":\"\"},{\"rank\":266,\"nickname\":\"Seinaru\",\"points\":\"3085.00\",\"prize\":\"\"},{\"rank\":267,\"nickname\":\"piao-A\",\"points\":\"3059.00\",\"prize\":\"\"},{\"rank\":268,\"nickname\":\"Pause-\",\"points\":\"3042.00\",\"prize\":\"\"},{\"rank\":269,\"nickname\":\"Seanyayaying\",\"points\":\"3031.00\",\"prize\":\"\"},{\"rank\":270,\"nickname\":\"fyyin\",\"points\":\"2966.00\",\"prize\":\"\"}]}"
}